zinvest_trade_api/__init__.py
zinvest_trade_api/common.py
zinvest_trade_api/stream.py
zinvest_trade_api-0.0.4.dist-info/LICENSE
zinvest_trade_api-0.0.4.dist-info/METADATA
zinvest_trade_api-0.0.4.dist-info/WHEEL
zinvest_trade_api-0.0.4.dist-info/top_level.txt
zinvest_trade_api-0.0.4.dist-info/RECORD
