Metadata-Version: 2.1
Name: zinvest-trade-api
Version: 0.0.4
Summary: Zinvest API python client
Home-page: https://github.com/zvsts/zinvest-trade-api-python
Author: zinvest
Author-email: api@zvsthk.com
License: UNKNOWN
Keywords: financial,stock,market data,api,trade
Platform: UNKNOWN
Classifier: Programming Language :: Python :: 3
Classifier: License :: OSI Approved :: MIT License
Classifier: Operating System :: OS Independent
License-File: LICENSE
Requires-Dist: python-dateutil (==2.8.1)
Requires-Dist: msgpack (==1.0.2)
Requires-Dist: websockets (==8.0)
